EmotionallyIntelligentUnit/__init__.py
EmotionallyIntelligentUnit-0.1.0a0.dist-info/LICENSE
EmotionallyIntelligentUnit-0.1.0a0.dist-info/METADATA
EmotionallyIntelligentUnit-0.1.0a0.dist-info/WHEEL
EmotionallyIntelligentUnit-0.1.0a0.dist-info/top_level.txt
EmotionallyIntelligentUnit-0.1.0a0.dist-info/RECORD
